evmcodegen/__init__.py
evmcodegen/__main__.py
evmcodegen/codegen.py
evmcodegen/distributions.py
evmcodegen/generators/__init__.py
evmcodegen/generators/base.py
evmcodegen/generators/distribution.py
evmcodegen/generators/rnn.py
evmcodegen/mutator/__init__.py
evmcodegen/utils/__init__.py
evmcodegen/utils/random.py
evmcodegen/weights/rnn_ethcontract_config.json
evmcodegen/weights/rnn_ethcontract_vocab.json
evmcodegen/weights/rnn_ethcontract_weights.hdf5
evmcodegen-0.1.3.dist-info/METADATA
evmcodegen-0.1.3.dist-info/WHEEL
evmcodegen-0.1.3.dist-info/top_level.txt
evmcodegen-0.1.3.dist-info/RECORD
