Metadata-Version: 2.1
Name: evmcodegen
Version: 0.1.3
Summary: A synthetic evm bytecode generation library and cmdline utility to fuzz the ethereum stack machine
Home-page: https://github.com/tintinweb/evmcodegen
Author: tintinweb
Author-email: tintinweb@oststrom.com
License: GPLv2
Download-URL: https://github.com/tintinweb/evmcodegen/tarball/v0.1.3
Keywords: evmdasm,ethereum,blockchain,evm,code,fuzzer,fuzzing
Platform: UNKNOWN
Requires-Dist: evmdasm
Provides-Extra: rnn
Requires-Dist: textgenrnn; extra == 'rnn'
